formify/SaveLoad.py
formify/__init__.py
formify/_rember_ui_settings.py
formify/_save_load_helpers.py
formify/app.py
formify/formify.ico
formify/install_ui.py
formify/localization.py
formify/splash.png
formify/style.css
formify/window.py
formify/windows.css
formify/controls/ConditionalForm.py
formify/controls/ControlButton.py
formify/controls/ControlCheckbox.py
formify/controls/ControlDiff.py
formify/controls/ControlFile.py
formify/controls/ControlFloat.py
formify/controls/ControlHtml.py
formify/controls/ControlImage.py
formify/controls/ControlInt.py
formify/controls/ControlList.py
formify/controls/ControlMatplotlib.py
formify/controls/ControlMessagebox.py
formify/controls/ControlProgress.py
formify/controls/ControlPyvista.py
formify/controls/ControlRadio.py
formify/controls/ControlSelect.py
formify/controls/ControlSelectSidebar.py
formify/controls/ControlSlider.py
formify/controls/ControlTable.py
formify/controls/ControlText.py
formify/controls/ControlTextarea.py
formify/controls/Form.py
formify/controls/ListForm.py
formify/controls/_ControlTree.py
formify/controls/__init__.py
formify/controls/_base.py
formify/controls/_events.py
formify/controls/_item_base.py
formify/controls/_value_base.py
formify/layout/SidebarContentView.py
formify/layout/__init__.py
formify/layout/conditional.py
formify/layout/headings.py
formify/layout/layouts.py
formify/layout/segments.py
formify/tools/__init__.py
formify/tools/background_method.py
formify/tools/dialogs.py
formify/tools/file_dialogs.py
formify/tools/misc.py
formify/tools/relationship.py
formify/tools/single_instance.py
formify-1.3.4.dist-info/METADATA
formify-1.3.4.dist-info/WHEEL
formify-1.3.4.dist-info/entry_points.txt
formify-1.3.4.dist-info/top_level.txt
formify-1.3.4.dist-info/RECORD
