Metadata-Version: 2.1
Name: formify
Version: 1.3.4
Summary: An easy to use UI Framework on top of Qt.
Home-page: https://github.com/TorbenFricke/formify
Author: Torben Fricke
Author-email: mail@torben.co
Classifier: Programming Language :: Python :: 3
Classifier: License :: OSI Approved :: MIT License
Classifier: Operating System :: OS Independent
Requires-Python: >=3.8
Requires-Dist: pyside6
Requires-Dist: pyinstaller
